era.py
setup.cfg
setup.py
era.egg-info/PKG-INFO
era.egg-info/SOURCES.txt
era.egg-info/dependency_links.txt
era.egg-info/not-zip-safe
era.egg-info/requires.txt
era.egg-info/top_level.txt