Metadata-Version: 1.1
Name: era
Version: 1.1
Summary: Sane date and time tools for Python.
Home-page: https://github.com/WiFast/era
Author: WiFast
Author-email: rgb@wifast.com
License: BSD-derived
Keywords: date time timezone
Platform: UNKNOWN
Classifier: Intended Audience :: Developers
Classifier: Programming Language :: Python
Classifier: Programming Language :: Python :: 2
Classifier: Programming Language :: Python :: 2.7
Classifier: License :: OSI Approved :: BSD License
